midas_weather/__init__.py
midas_weather/analysis.py
midas_weather/download.py
midas_weather/meta.py
midas_weather/module.py
midas_weather/simulator.py
midas_weather/model/__init__.py
midas_weather/model/current.py
midas_weather/model/forecast.py
midas_weather/model/provider.py
midas_weather-2.0.3.dist-info/LICENSE
midas_weather-2.0.3.dist-info/METADATA
midas_weather-2.0.3.dist-info/WHEEL
midas_weather-2.0.3.dist-info/top_level.txt
midas_weather-2.0.3.dist-info/RECORD
