Metadata-Version: 2.2
Name: midas-weather
Version: 2.0.3
Summary: A Midas module for weather datasets.
Author-email: Stephan Balduin <stephan.balduin@offis.de>
Project-URL: Documentation, https://midas-mosaik.gitlab.io/midas
Requires-Python: >=3.8
License-File: LICENSE
Requires-Dist: midas-mosaik~=2.0.0
Requires-Dist: mosaik_api
Requires-Dist: matplotlib
Requires-Dist: numpy
Requires-Dist: pandas
Requires-Dist: tables
Requires-Dist: wget
